sconf/__init__.py
st_config-0.0.5.dist-info/LICENSE
st_config-0.0.5.dist-info/METADATA
st_config-0.0.5.dist-info/WHEEL
st_config-0.0.5.dist-info/top_level.txt
st_config-0.0.5.dist-info/RECORD
