Metadata-Version: 2.1
Name: st-config
Version: 0.0.5
Summary: Singleton config for python
Home-page: https://github.com/cheddars/singleton-config
Author: cheddars
Author-email: nezahrish@gmail.com
License: MIT
Platform: UNKNOWN
Classifier: Programming Language :: Python :: 3
Classifier: License :: OSI Approved :: MIT License
Classifier: Operating System :: OS Independent
License-File: LICENSE
